mathprocessing/__init__.py
mathprocessing/math.py
mathprocessing/system.py
mathprocessing/caculation/__init__.py
mathprocessing/caculation/service.py
Math_Processing-0.1.2.311149.dist-info/LICENSE
Math_Processing-0.1.2.311149.dist-info/METADATA
Math_Processing-0.1.2.311149.dist-info/WHEEL
Math_Processing-0.1.2.311149.dist-info/top_level.txt
Math_Processing-0.1.2.311149.dist-info/RECORD
