Metadata-Version: 2.1
Name: Math-Processing
Version: 0.1.2.311149
Summary: Basic Digital Processing
Home-page: UNKNOWN
Author: Yile Wang
Author-email: 36210280@qq.com
License: GPL
Platform: UNKNOWN
Requires-Python: >=2.7
License-File: LICENSE
